escavador/__init__.py
escavador/api.py
escavador/exceptions.py
escavador/method.py
escavador/resources/__init__.py
escavador/resources/helpers/__init__.py
escavador/resources/helpers/consume_cursor.py
escavador/resources/helpers/documento.py
escavador/resources/helpers/endpoint.py
escavador/resources/helpers/enums.py
escavador/resources/helpers/enums_v1.py
escavador/resources/helpers/enums_v2.py
escavador/resources/helpers/lista_resultados.py
escavador/v1/__init__.py
escavador/v1/resources/__init__.py
escavador/v1/resources/busca.py
escavador/v1/resources/busca_assincrona.py
escavador/v1/resources/callback.py
escavador/v1/resources/diario_oficial.py
escavador/v1/resources/instituicao.py
escavador/v1/resources/jurisprudencia.py
escavador/v1/resources/legislacao.py
escavador/v1/resources/monitoramento_diario.py
escavador/v1/resources/monitoramento_tribunal.py
escavador/v1/resources/movimentacao.py
escavador/v1/resources/pessoa.py
escavador/v1/resources/processo.py
escavador/v1/resources/saldo.py
escavador/v1/resources/tribunal.py
escavador/v2/__init__.py
escavador/v2/resources/__init__.py
escavador/v2/resources/envolvido.py
escavador/v2/resources/movimentacao.py
escavador/v2/resources/processo.py
escavador/v2/resources/tribunal.py
escavador-0.11.2.dist-info/METADATA
escavador-0.11.2.dist-info/WHEEL
escavador-0.11.2.dist-info/licenses/LICENSE
escavador-0.11.2.dist-info/RECORD
