Metadata-Version: 2.4
Name: escavador
Version: 0.11.2
Summary: A library to interact with Escavador API
License: MIT
License-File: LICENSE
Keywords: escavador,api,python
Author: Gabriel
Author-email: gabriel@escavador.com
Requires-Python: >=3.7,<4.0
Classifier: License :: OSI Approved :: MIT License
Classifier: Programming Language :: Python :: 3
Classifier: Programming Language :: Python :: 3.7
Classifier: Programming Language :: Python :: 3.8
Classifier: Programming Language :: Python :: 3.9
Classifier: Programming Language :: Python :: 3.10
Classifier: Programming Language :: Python :: 3.11
Classifier: Programming Language :: Python :: 3.12
Classifier: Programming Language :: Python :: 3.13
Classifier: Programming Language :: Python :: 3.14
Requires-Dist: importlib_metadata
Requires-Dist: python-dotenv (>=0.19.2)
Requires-Dist: ratelimit
Requires-Dist: requests (>=2.27.1)
Project-URL: Documentation, https://api.escavador.com/docs/
Project-URL: Homepage, https://www.escavador.com
Project-URL: Repository, https://github.com/Escavador/escavador-python
